{
    "name": "dsa5-drag-ruler",
    "id": "dsa5-drag-ruler",
    "title": "The Dark Eye 5th Ed. - Drag Ruler Integration",
    "description": "Custom provider for drag ruler, providing out of the box compatibility for TDE5/DSA5.",
    "version": "1.11.0",
    "minimumCoreVersion": "11",
    "compatibility": {
        "minimum": "11",
        "verified": "11",
        "maximum": "11"
    },
    "authors": [
        {
            "name": "Rapunzel77",
            "url": "https://github.com/Rapunzel77/dsa5-drag-ruler",
            "discord": "Rapunzel_77#7051"
        }
    ],
    "relationships": {
        "systems": [
            {
                "id": "dsa5",
                "manifest": "https://raw.githubusercontent.com/Plushtoast/dsa5-foundryVTT/foundry10/system.json",
                "compatibility": {
                    "minimum": "4.0.6",
                    "verified": "5.0.5"
                }
            }
        ],
        "requires": [
            {
                "id": "drag-ruler",
                "type": "module",
                "manifest": "https://raw.githubusercontent.com/manuelVo/foundryvtt-drag-ruler/master/module.json",
                "compatibility": {
                    "minimum": "1.12.8",
                    "verified": "1.13.8"
                }
            }
        ]
    },
    "esmodules": [
        "scripts/main.js"
    ],
    "languages": [
        {
            "lang": "de",
            "name": "Deutsch",
            "path": "lang/de.json"
        },
        {
            "lang": "en",
            "name": "English",
            "path": "lang/en.json"
        }
    ],
    "license" : "LICENSE",
    "readme" : "README.md",
    "bugs" : "https://github.com/Rapunzel77/dsa5-drag-ruler/issues",
    "changelog" : "https://github.com/Rapunzel77/dsa5-drag-ruler/releases/latest",
    "url": "https://github.com/Rapunzel77/dsa5-drag-ruler",
    "manifest": "https://github.com/Rapunzel77/dsa5-drag-ruler/releases/latest/download/module.json",
    "download": "https://github.com/Rapunzel77/dsa5-drag-ruler/archive/refs/tags/1.11.0.zip"
}